{
  "generated_at": "2026-04-30T16:53:41Z",
  "window_hours": 24,
  "token_count": 18,
  "tokens": [
    {
      "rank": 1,
      "symbol": "FLORK",
      "token_address": "0xce82213c4bae42e1c04880ea64a53eef73e195de",
      "score": 47.4,
      "severity": "none",
      "signals": 12,
      "last_seen": "2026-04-30 10:48:13",
      "chart_enabled": false,
      "price_change_24h": 43.16,
      "market_cap_usd": 4606948.0,
      "liquidity_usd": 297681.52,
      "holder_count": 0,
      "liquidity_change_24h_pct": 0.0,
      "holder_count_change_24h_pct": 0.0,
      "top10_pct": 100.0,
      "volume_24h_usd": 1043059.88,
      "volume_1h_usd": 3.88,
      "logo_url": "https://cdn.dexscreener.com/cms/images/frfvp2MJVhSdFPdj?width=800&height=800&quality=95&format=auto"
    },
    {
      "rank": 2,
      "symbol": "ETH",
      "token_address": "0x0000000000000000000000000000000000000000",
      "score": 41.7,
      "severity": "critical",
      "signals": 4,
      "last_seen": "2026-04-30 14:26:10",
      "chart_enabled": false,
      "price_change_24h": -0.32,
      "market_cap_usd": 200721.0,
      "liquidity_usd": 1261941.03,
      "holder_count": 0,
      "liquidity_change_24h_pct": 0.0,
      "holder_count_change_24h_pct": 0.0,
      "top10_pct": 100.0,
      "volume_24h_usd": 7842295.16,
      "volume_1h_usd": 6804.32
    },
    {
      "rank": 3,
      "symbol": "MUSK",
      "token_address": "0xd2cdcb399438d3d088a6bb3a4f5af39a3ab01110",
      "score": 39.0,
      "severity": "none",
      "signals": 3,
      "last_seen": "2026-04-30 10:51:13",
      "chart_enabled": false,
      "price_change_24h": -20.95,
      "market_cap_usd": 163976.0,
      "liquidity_usd": 40913.7,
      "holder_count": 0,
      "liquidity_change_24h_pct": 0.0,
      "holder_count_change_24h_pct": 0.0,
      "top10_pct": 100.0,
      "volume_24h_usd": 563440.96,
      "volume_1h_usd": 0.0,
      "logo_url": "https://cdn.dexscreener.com/cms/images/Alf0CV5xjf7vJVrb?width=800&height=800&quality=95&format=auto"
    },
    {
      "rank": 4,
      "symbol": "AIB",
      "token_address": "0xb3a0f70c913aa04404bd177be9e20b47613830b6",
      "score": 35.6,
      "severity": "none",
      "signals": 14,
      "last_seen": "2026-04-30 10:51:03",
      "chart_enabled": false,
      "price_change_24h": -16.93,
      "market_cap_usd": 2217957.0,
      "liquidity_usd": 215284.11,
      "holder_count": 0,
      "liquidity_change_24h_pct": -13.96,
      "holder_count_change_24h_pct": 0.0,
      "top10_pct": 100.0,
      "volume_24h_usd": 889355.61,
      "volume_1h_usd": 0.0,
      "logo_url": "https://cdn.dexscreener.com/cms/images/5lmSMcgPJnbFPUtP?width=800&height=800&quality=95&format=auto"
    },
    {
      "rank": 5,
      "symbol": "CMD",
      "token_address": "0xae42f183554d369ee98b7b1980bea3761f47abc3",
      "score": 35.3,
      "severity": "critical",
      "signals": 9,
      "last_seen": "2026-04-30 14:09:57",
      "chart_enabled": false,
      "price_change_24h": -20.05,
      "market_cap_usd": 1217243.0,
      "liquidity_usd": 508643.11,
      "holder_count": 0,
      "liquidity_change_24h_pct": -23.77,
      "holder_count_change_24h_pct": 0.0,
      "top10_pct": 100.0,
      "volume_24h_usd": 166299.8,
      "volume_1h_usd": 12069.39
    },
    {
      "rank": 6,
      "symbol": "WETH",
      "token_address": "0xc02aaa39b223fe8d0a0e5c4f27ead9083c756cc2",
      "score": 33.5,
      "severity": "none",
      "signals": 14,
      "last_seen": "2026-04-30 10:47:55",
      "chart_enabled": false,
      "price_change_24h": -0.4,
      "market_cap_usd": 4103625297.0,
      "liquidity_usd": 6747433.46,
      "holder_count": 0,
      "liquidity_change_24h_pct": 0.91,
      "holder_count_change_24h_pct": 0.0,
      "top10_pct": 100.0,
      "volume_24h_usd": 69811292.84,
      "volume_1h_usd": 491.95,
      "logo_url": "https://cdn.dexscreener.com/cms/images/e7ad3f643e8706e541538413f2afad46f18cafb430606caae3c70c0f7425c16e?width=800&height=800&quality=95&format=auto"
    },
    {
      "rank": 7,
      "symbol": "AI",
      "token_address": "0x4d7078ddd6ccfed2f85db5b7d3ff16828d378d48",
      "score": 32.7,
      "severity": "low",
      "signals": 13,
      "last_seen": "2026-04-30 15:55:31",
      "chart_enabled": false,
      "price_change_24h": -10.99,
      "market_cap_usd": 14345680.0,
      "liquidity_usd": 1553848.29,
      "holder_count": 0,
      "liquidity_change_24h_pct": 0.0,
      "holder_count_change_24h_pct": 0.0,
      "top10_pct": 100.0,
      "volume_24h_usd": 2950044.04,
      "volume_1h_usd": 0.0,
      "logo_url": "https://cdn.dexscreener.com/cms/images/3hIjLxh3bMhiVc8L?width=800&height=800&quality=95&format=auto"
    },
    {
      "rank": 8,
      "symbol": "WISH",
      "token_address": "0xf7472c606596943d2b5a9769d7e6cc273306b4ef",
      "score": 31.7,
      "severity": "none",
      "signals": 2,
      "last_seen": "2026-04-30 11:31:03",
      "chart_enabled": false,
      "price_change_24h": 2908.0,
      "market_cap_usd": 68906.0,
      "liquidity_usd": 25275.8,
      "holder_count": 0,
      "liquidity_change_24h_pct": 0.0,
      "holder_count_change_24h_pct": 0.0,
      "top10_pct": 100.0,
      "volume_24h_usd": 62077.72,
      "volume_1h_usd": 1363.11,
      "logo_url": "https://cdn.dexscreener.com/cms/images/5-yWFPjcNyeA7Ju_?width=800&height=800&quality=95&format=auto"
    },
    {
      "rank": 9,
      "symbol": "MYSTERY",
      "token_address": "0x45547ab0100f5e8b158258b6d94d7586de69fc21",
      "score": 30.6,
      "severity": "none",
      "signals": 15,
      "last_seen": "2026-04-30 15:39:29",
      "chart_enabled": false,
      "price_change_24h": -45.22,
      "market_cap_usd": 2600130.0,
      "liquidity_usd": 213234.04,
      "holder_count": 0,
      "liquidity_change_24h_pct": -32.34,
      "holder_count_change_24h_pct": 0.0,
      "top10_pct": 100.0,
      "volume_24h_usd": 1299597.85,
      "volume_1h_usd": 0.0,
      "logo_url": "https://cdn.dexscreener.com/cms/images/u4icy_uHFUb4rxpV?width=800&height=800&quality=95&format=auto"
    },
    {
      "rank": 10,
      "symbol": "UPEG",
      "token_address": "0x44b28991b167582f18ba0259e0173176ca125505",
      "score": 30.6,
      "severity": "none",
      "signals": 15,
      "last_seen": "2026-04-30 15:24:34",
      "chart_enabled": false,
      "price_change_24h": 27.13,
      "market_cap_usd": 7918434.0,
      "liquidity_usd": 120215.46,
      "holder_count": 0,
      "liquidity_change_24h_pct": -9.1,
      "holder_count_change_24h_pct": 0.0,
      "top10_pct": 100.0,
      "volume_24h_usd": 923706.76,
      "volume_1h_usd": 0.0,
      "logo_url": "https://cdn.dexscreener.com/cms/images/7JZSyzyCBXJ4m5uJ?width=800&height=800&quality=95&format=auto"
    },
    {
      "rank": 11,
      "symbol": "ASTEROID",
      "token_address": "0xf280b16ef293d8e534e370794ef26bf312694126",
      "score": 29.8,
      "severity": "none",
      "signals": 15,
      "last_seen": "2026-04-30 10:51:37",
      "chart_enabled": false,
      "price_change_24h": 32.44,
      "market_cap_usd": 152291534.0,
      "liquidity_usd": 3941766.35,
      "holder_count": 0,
      "liquidity_change_24h_pct": 6.77,
      "holder_count_change_24h_pct": 0.0,
      "top10_pct": 100.0,
      "volume_24h_usd": 5241294.35,
      "volume_1h_usd": 0.0,
      "logo_url": "https://cdn.dexscreener.com/cms/images/m9Re46s3EcIf--TW?width=800&height=800&quality=95&format=auto"
    },
    {
      "rank": 12,
      "symbol": "CLAWD",
      "token_address": "0x46d03ff0fe7e539804678530ea5d6289a76c1ade",
      "score": 29.7,
      "severity": "none",
      "signals": 6,
      "last_seen": "2026-04-30 15:41:28",
      "chart_enabled": false,
      "price_change_24h": -20.98,
      "market_cap_usd": 1132199.0,
      "liquidity_usd": 107398.9,
      "holder_count": 0,
      "liquidity_change_24h_pct": 0.0,
      "holder_count_change_24h_pct": 0.0,
      "top10_pct": 100.0,
      "volume_24h_usd": 783806.59,
      "volume_1h_usd": 38.27,
      "logo_url": "https://cdn.dexscreener.com/cms/images/700NoGy6ZoDPBaD5?width=800&height=800&quality=95&format=auto"
    },
    {
      "rank": 13,
      "symbol": "ASTEROID",
      "token_address": "0xaff2565091e7207191dbe340b8528d02fa78d044",
      "score": 29.6,
      "severity": "none",
      "signals": 13,
      "last_seen": "2026-04-30 09:14:36",
      "chart_enabled": false,
      "price_change_24h": -20.21,
      "market_cap_usd": 6233146.0,
      "liquidity_usd": 375314.32,
      "holder_count": 0,
      "liquidity_change_24h_pct": -23.43,
      "holder_count_change_24h_pct": 0.0,
      "top10_pct": 100.0,
      "volume_24h_usd": 1260847.93,
      "volume_1h_usd": 0.0,
      "logo_url": "https://cdn.dexscreener.com/cms/images/j2LGvafk8Kq_GJEN?width=800&height=800&quality=95&format=auto"
    },
    {
      "rank": 14,
      "symbol": "GRUG",
      "token_address": "0xf62de9648ba8ec86c3d5ca88ff5252d3a6ce666d",
      "score": 28.6,
      "severity": "none",
      "signals": 1,
      "last_seen": "2026-04-30 11:20:04",
      "chart_enabled": false,
      "price_change_24h": 305.0,
      "market_cap_usd": 76750.0,
      "liquidity_usd": 23399.33,
      "holder_count": 0,
      "liquidity_change_24h_pct": 0.0,
      "holder_count_change_24h_pct": 0.0,
      "top10_pct": 100.0,
      "volume_24h_usd": 95312.17,
      "volume_1h_usd": 24617.97,
      "logo_url": "https://cdn.dexscreener.com/cms/images/6DYtYiT_hTGSC6nO?width=800&height=800&quality=95&format=auto"
    },
    {
      "rank": 15,
      "symbol": "GOBLIN",
      "token_address": "0x696969a73cfe28165e94f0924d3c940a55bc483e",
      "score": 28.3,
      "severity": "none",
      "signals": 1,
      "last_seen": "2026-04-30 02:28:02",
      "chart_enabled": false,
      "price_change_24h": -54.7,
      "market_cap_usd": 309026.0,
      "liquidity_usd": 56649.81,
      "holder_count": 0,
      "liquidity_change_24h_pct": 0.0,
      "holder_count_change_24h_pct": 0.0,
      "top10_pct": 100.0,
      "volume_24h_usd": 939347.55,
      "volume_1h_usd": 0.0,
      "logo_url": "https://cdn.dexscreener.com/cms/images/885dba968f0dc681ebb3b7f0f3e3fdfb68e5e6e41a7479b75568f991dddaac5a?width=800&height=800&quality=95&format=auto"
    },
    {
      "rank": 16,
      "symbol": "ELIEN",
      "token_address": "0xc7e4254a72169fdf7a2e080462724f2f642daf7e",
      "score": 27.8,
      "severity": "none",
      "signals": 13,
      "last_seen": "2026-04-30 10:49:49",
      "chart_enabled": false,
      "price_change_24h": 5.14,
      "market_cap_usd": 476306.0,
      "liquidity_usd": 78009.06,
      "holder_count": 0,
      "liquidity_change_24h_pct": 13.67,
      "holder_count_change_24h_pct": 0.0,
      "top10_pct": 100.0,
      "volume_24h_usd": 291917.7,
      "volume_1h_usd": 0.0,
      "logo_url": "https://cdn.dexscreener.com/cms/images/zl1bTcUhxE3VoDK_?width=800&height=800&quality=95&format=auto"
    },
    {
      "rank": 17,
      "symbol": "KIRKSLOP",
      "token_address": "0xa67b0d5c199939aab99a3d0b2adb4267d6cc1985",
      "score": 27.1,
      "severity": "none",
      "signals": 4,
      "last_seen": "2026-04-30 06:31:38",
      "chart_enabled": false,
      "price_change_24h": 4521.0,
      "market_cap_usd": 109988.0,
      "liquidity_usd": 29396.18,
      "holder_count": 0,
      "liquidity_change_24h_pct": 0.0,
      "holder_count_change_24h_pct": 0.0,
      "top10_pct": 100.0,
      "volume_24h_usd": 373896.07,
      "volume_1h_usd": 0.0,
      "logo_url": "https://cdn.dexscreener.com/cms/images/JYV_SFbrIxBmxUgZ?width=800&height=800&quality=95&format=auto"
    },
    {
      "rank": 18,
      "symbol": "MIDI",
      "token_address": "0x08d4fcd293a1572488d016756ebe039160ebc58f",
      "score": 27.1,
      "severity": "none",
      "signals": 2,
      "last_seen": "2026-04-30 02:30:10",
      "chart_enabled": false,
      "price_change_24h": -23.33,
      "market_cap_usd": 17098.0,
      "liquidity_usd": 10518.1,
      "holder_count": 0,
      "liquidity_change_24h_pct": -28.56,
      "holder_count_change_24h_pct": 0.0,
      "top10_pct": 100.0,
      "volume_24h_usd": 3675.25,
      "volume_1h_usd": 13.35,
      "logo_url": "https://cdn.dexscreener.com/cms/images/_W5K0CFLS-_q13hc?width=800&height=800&quality=95&format=auto"
    }
  ]
}