{
  "generated_at": "2026-04-29T13:08:35Z",
  "window_hours": 24,
  "token_count": 18,
  "tokens": [
    {
      "rank": 1,
      "symbol": "ELIEN",
      "token_address": "0xc7e4254a72169fdf7a2e080462724f2f642daf7e",
      "score": 37.1,
      "severity": "none",
      "signals": 12,
      "last_seen": "2026-04-29 12:54:44",
      "chart_enabled": false,
      "price_change_24h": -67.02,
      "market_cap_usd": 453105.0,
      "liquidity_usd": 76251.58,
      "holder_count": 0,
      "liquidity_change_24h_pct": 0.0,
      "holder_count_change_24h_pct": 0.0,
      "top10_pct": 100.0,
      "volume_24h_usd": 784926.59,
      "volume_1h_usd": 33.39,
      "logo_url": "https://cdn.dexscreener.com/cms/images/zl1bTcUhxE3VoDK_?width=800&height=800&quality=95&format=auto"
    },
    {
      "rank": 2,
      "symbol": "WETH",
      "token_address": "0xc02aaa39b223fe8d0a0e5c4f27ead9083c756cc2",
      "score": 36.0,
      "severity": "none",
      "signals": 13,
      "last_seen": "2026-04-29 12:49:18",
      "chart_enabled": false,
      "price_change_24h": 2.13,
      "market_cap_usd": 4205133357.0,
      "liquidity_usd": 6803886.09,
      "holder_count": 0,
      "liquidity_change_24h_pct": 0.0,
      "holder_count_change_24h_pct": 0.0,
      "top10_pct": 100.0,
      "volume_24h_usd": 56969582.87,
      "volume_1h_usd": 16883.42,
      "logo_url": "https://cdn.dexscreener.com/cms/images/e7ad3f643e8706e541538413f2afad46f18cafb430606caae3c70c0f7425c16e?width=800&height=800&quality=95&format=auto"
    },
    {
      "rank": 3,
      "symbol": "AIB",
      "token_address": "0xb3a0f70c913aa04404bd177be9e20b47613830b6",
      "score": 35.7,
      "severity": "critical",
      "signals": 13,
      "last_seen": "2026-04-29 12:43:37",
      "chart_enabled": false,
      "price_change_24h": -16.48,
      "market_cap_usd": 3149368.0,
      "liquidity_usd": 256631.07,
      "holder_count": 0,
      "liquidity_change_24h_pct": 0.0,
      "holder_count_change_24h_pct": 0.0,
      "top10_pct": 100.0,
      "volume_24h_usd": 649527.32,
      "volume_1h_usd": 0.0,
      "logo_url": "https://cdn.dexscreener.com/cms/images/5lmSMcgPJnbFPUtP?width=800&height=800&quality=95&format=auto"
    },
    {
      "rank": 4,
      "symbol": "EWON",
      "token_address": "0xfcda4527b16be15de033a9259861a5632d5b9b76",
      "score": 34.2,
      "severity": "none",
      "signals": 1,
      "last_seen": "2026-04-29 01:15:02",
      "chart_enabled": false,
      "price_change_24h": 147.0,
      "market_cap_usd": 10259.0,
      "liquidity_usd": 7443.55,
      "holder_count": 0,
      "liquidity_change_24h_pct": 0.0,
      "holder_count_change_24h_pct": 0.0,
      "top10_pct": 100.0,
      "volume_24h_usd": 251070.71,
      "volume_1h_usd": 0.0,
      "logo_url": "https://cdn.dexscreener.com/cms/images/UDafMFM9sKDITADv?width=800&height=800&quality=95&format=auto"
    },
    {
      "rank": 5,
      "symbol": "UPEG",
      "token_address": "0x44b28991b167582f18ba0259e0173176ca125505",
      "score": 34.2,
      "severity": "none",
      "signals": 16,
      "last_seen": "2026-04-29 11:15:39",
      "chart_enabled": false,
      "price_change_24h": -4.53,
      "market_cap_usd": 7675025.0,
      "liquidity_usd": 94730.39,
      "holder_count": 0,
      "liquidity_change_24h_pct": 0.0,
      "holder_count_change_24h_pct": 0.0,
      "top10_pct": 100.0,
      "volume_24h_usd": 1237864.47,
      "volume_1h_usd": 0.0,
      "logo_url": "https://cdn.dexscreener.com/cms/images/7JZSyzyCBXJ4m5uJ?width=800&height=800&quality=95&format=auto"
    },
    {
      "rank": 6,
      "symbol": "ASTEROID",
      "token_address": "0xaff2565091e7207191dbe340b8528d02fa78d044",
      "score": 34.0,
      "severity": "medium",
      "signals": 12,
      "last_seen": "2026-04-29 11:15:15",
      "chart_enabled": false,
      "price_change_24h": 53.94,
      "market_cap_usd": 10935411.0,
      "liquidity_usd": 497017.04,
      "holder_count": 0,
      "liquidity_change_24h_pct": 32.58,
      "holder_count_change_24h_pct": 0.0,
      "top10_pct": 100.0,
      "volume_24h_usd": 5763301.59,
      "volume_1h_usd": 0.0,
      "logo_url": "https://cdn.dexscreener.com/cms/images/j2LGvafk8Kq_GJEN?width=800&height=800&quality=95&format=auto"
    },
    {
      "rank": 7,
      "symbol": "CMD",
      "token_address": "0xae42f183554d369ee98b7b1980bea3761f47abc3",
      "score": 32.8,
      "severity": "low",
      "signals": 8,
      "last_seen": "2026-04-29 12:43:24",
      "chart_enabled": false,
      "price_change_24h": -22.81,
      "market_cap_usd": 1927586.0,
      "liquidity_usd": 647833.88,
      "holder_count": 0,
      "liquidity_change_24h_pct": 0.0,
      "holder_count_change_24h_pct": 0.0,
      "top10_pct": 100.0,
      "volume_24h_usd": 278094.1,
      "volume_1h_usd": 10806.84
    },
    {
      "rank": 8,
      "symbol": "USDC",
      "token_address": "0xa0b86991c6218b36c1d19d4a2e9eb0ce3606eb48",
      "score": 30.7,
      "severity": "critical",
      "signals": 14,
      "last_seen": "2026-04-29 12:39:25",
      "chart_enabled": false,
      "price_change_24h": 0.01,
      "market_cap_usd": 77575307237.0,
      "liquidity_usd": 884059.17,
      "holder_count": 0,
      "liquidity_change_24h_pct": 0.0,
      "holder_count_change_24h_pct": 0.0,
      "top10_pct": 100.0,
      "volume_24h_usd": 183475291.15,
      "volume_1h_usd": 48603.02
    },
    {
      "rank": 9,
      "symbol": "WOJAK",
      "token_address": "0x8de39b057cc6522230ab19c0205080a8663331ef",
      "score": 30.2,
      "severity": "none",
      "signals": 10,
      "last_seen": "2026-04-29 07:08:27",
      "chart_enabled": false,
      "price_change_24h": -3.67,
      "market_cap_usd": 24605442.0,
      "liquidity_usd": 958213.93,
      "holder_count": 0,
      "liquidity_change_24h_pct": -13.51,
      "holder_count_change_24h_pct": 0.0,
      "top10_pct": 100.0,
      "volume_24h_usd": 763796.12,
      "volume_1h_usd": 0.0,
      "logo_url": "https://cdn.dexscreener.com/cms/images/2e14770d490f8fd236b55f378300bae39c9881ac420b5c3304f72cf065f06ea9?width=800&height=800&quality=95&format=auto"
    },
    {
      "rank": 10,
      "symbol": "MYSTERY",
      "token_address": "0x45547ab0100f5e8b158258b6d94d7586de69fc21",
      "score": 29.6,
      "severity": "critical",
      "signals": 14,
      "last_seen": "2026-04-29 12:31:04",
      "chart_enabled": false,
      "price_change_24h": 13.15,
      "market_cap_usd": 5467361.0,
      "liquidity_usd": 307302.65,
      "holder_count": 0,
      "liquidity_change_24h_pct": 41.04,
      "holder_count_change_24h_pct": 0.0,
      "top10_pct": 100.0,
      "volume_24h_usd": 1759569.66,
      "volume_1h_usd": 17.38,
      "logo_url": "https://cdn.dexscreener.com/cms/images/u4icy_uHFUb4rxpV?width=800&height=800&quality=95&format=auto"
    },
    {
      "rank": 11,
      "symbol": "ASTEROID",
      "token_address": "0xf280b16ef293d8e534e370794ef26bf312694126",
      "score": 28.9,
      "severity": "critical",
      "signals": 13,
      "last_seen": "2026-04-29 09:08:22",
      "chart_enabled": false,
      "price_change_24h": 3.07,
      "market_cap_usd": 124086673.0,
      "liquidity_usd": 3609973.03,
      "holder_count": 0,
      "liquidity_change_24h_pct": 0.0,
      "holder_count_change_24h_pct": 0.0,
      "top10_pct": 100.0,
      "volume_24h_usd": 5271258.81,
      "volume_1h_usd": 0.0,
      "logo_url": "https://cdn.dexscreener.com/cms/images/m9Re46s3EcIf--TW?width=800&height=800&quality=95&format=auto"
    },
    {
      "rank": 12,
      "symbol": "ALIENS",
      "token_address": "0xc77867d630dbe567d219a86fddbe7ef1f0670fdc",
      "score": 27.7,
      "severity": "none",
      "signals": 10,
      "last_seen": "2026-04-29 12:54:36",
      "chart_enabled": false,
      "price_change_24h": -11.95,
      "market_cap_usd": 995848.0,
      "liquidity_usd": 102345.32,
      "holder_count": 0,
      "liquidity_change_24h_pct": 0.0,
      "holder_count_change_24h_pct": 0.0,
      "top10_pct": 100.0,
      "volume_24h_usd": 202221.16,
      "volume_1h_usd": 593.53,
      "logo_url": "https://cdn.dexscreener.com/cms/images/23Xiptb-_VqaG_X_?width=800&height=800&quality=95&format=auto"
    },
    {
      "rank": 13,
      "symbol": "CLIPPY",
      "token_address": "0x5cc0846ea203ffdad359ad4c31a7dfb2f62e1110",
      "score": 26.9,
      "severity": "none",
      "signals": 8,
      "last_seen": "2026-04-29 12:32:46",
      "chart_enabled": false,
      "price_change_24h": -49.83,
      "market_cap_usd": 23221.0,
      "liquidity_usd": 14625.72,
      "holder_count": 0,
      "liquidity_change_24h_pct": 0.0,
      "holder_count_change_24h_pct": 0.0,
      "top10_pct": 100.0,
      "volume_24h_usd": 647895.84,
      "volume_1h_usd": 0.0,
      "logo_url": "https://cdn.dexscreener.com/cms/images/GnuL30fn-tXPCKCR?width=800&height=800&quality=95&format=auto"
    },
    {
      "rank": 14,
      "symbol": "KIMCHI",
      "token_address": "0x2b566950ba2298acef3c730cc0129b2f4fbd30a3",
      "score": 26.7,
      "severity": "none",
      "signals": 8,
      "last_seen": "2026-04-29 12:30:52",
      "chart_enabled": false,
      "price_change_24h": 35.63,
      "market_cap_usd": 1239999.0,
      "liquidity_usd": 110545.07,
      "holder_count": 0,
      "liquidity_change_24h_pct": 0.0,
      "holder_count_change_24h_pct": 0.0,
      "top10_pct": 100.0,
      "volume_24h_usd": 88760.76,
      "volume_1h_usd": 37.31,
      "logo_url": "https://cdn.dexscreener.com/cms/images/CTQmbsVMsAj7q097?width=800&height=800&quality=95&format=auto"
    },
    {
      "rank": 15,
      "symbol": "SCAMMAN",
      "token_address": "0xd2d576903f590c93050e695097b026dd3e9582b5",
      "score": 26.6,
      "severity": "critical",
      "signals": 14,
      "last_seen": "2026-04-29 12:59:01",
      "chart_enabled": false,
      "price_change_24h": -86.31,
      "market_cap_usd": 51066.0,
      "liquidity_usd": 42389.95,
      "holder_count": 0,
      "liquidity_change_24h_pct": 0.0,
      "holder_count_change_24h_pct": 0.0,
      "top10_pct": 100.0,
      "volume_24h_usd": 308034.24,
      "volume_1h_usd": 0.0,
      "logo_url": "https://cdn.dexscreener.com/cms/images/_G8a9kMT6fXt_Z5n?width=800&height=800&quality=95&format=auto"
    },
    {
      "rank": 16,
      "symbol": "KISHU",
      "token_address": "0xa2b4c0af19cc16a6cfacce81f192b024d625817d",
      "score": 25.4,
      "severity": "none",
      "signals": 5,
      "last_seen": "2026-04-29 06:17:37",
      "chart_enabled": false,
      "price_change_24h": 1.65,
      "market_cap_usd": 8643432.0,
      "liquidity_usd": 857728.49,
      "holder_count": 0,
      "liquidity_change_24h_pct": 0.0,
      "holder_count_change_24h_pct": 0.0,
      "top10_pct": 100.0,
      "volume_24h_usd": 28100.88,
      "volume_1h_usd": 0.0
    },
    {
      "rank": 17,
      "symbol": "UNICURVE",
      "token_address": "0xd400a048b726eba969449b342dc7c0e74187c0de",
      "score": 25.0,
      "severity": "critical",
      "signals": 8,
      "last_seen": "2026-04-29 08:14:28",
      "chart_enabled": false,
      "price_change_24h": 22.08,
      "market_cap_usd": 504494.0,
      "liquidity_usd": 88498.36,
      "holder_count": 0,
      "liquidity_change_24h_pct": 0.0,
      "holder_count_change_24h_pct": 0.0,
      "top10_pct": 100.0,
      "volume_24h_usd": 147823.05,
      "volume_1h_usd": 230.15,
      "logo_url": "https://cdn.dexscreener.com/cms/images/YcP_OtMv66WZHTvV?width=800&height=800&quality=95&format=auto"
    },
    {
      "rank": 18,
      "symbol": "MIDI",
      "token_address": "0x08d4fcd293a1572488d016756ebe039160ebc58f",
      "score": 24.7,
      "severity": "medium",
      "signals": 5,
      "last_seen": "2026-04-29 00:29:29",
      "chart_enabled": false,
      "price_change_24h": 989.0,
      "market_cap_usd": 36255.0,
      "liquidity_usd": 15523.6,
      "holder_count": 0,
      "liquidity_change_24h_pct": 0.0,
      "holder_count_change_24h_pct": 0.0,
      "top10_pct": 100.0,
      "volume_24h_usd": 105286.36,
      "volume_1h_usd": 0.0,
      "logo_url": "https://cdn.dexscreener.com/cms/images/_W5K0CFLS-_q13hc?width=800&height=800&quality=95&format=auto"
    }
  ]
}