{
  "generated_at": "2026-05-03T13:12:23Z",
  "token_count": 4,
  "tokens": [
    {
      "rank": 1,
      "symbol": "UCORE",
      "token_address": "0xd4e43c86334940a246daae8908c9b3cfb97c6817",
      "score": 45.3,
      "severity": "low",
      "mcap_usd": 372663.0,
      "lp_total_usd": 68397.39,
      "lp_total_usd_24h_ago": 0.0,
      "lp_total_change_24h_pct": 0.0,
      "holder_count": 0,
      "holder_count_24h_ago": 0,
      "holder_count_change_24h_pct": 0.0,
      "top10_pct": 100.0,
      "x_username": "",
      "x_url": "",
      "signal_age_hours": 1.26,
      "pair_address": "0xd7548773775d7d8c65bec6b615e907a06784e43b263a5db06d89e5dc665a1ed5",
      "dexscreener_url": "https://dexscreener.com/base/0xd7548773775d7d8c65bec6b615e907a06784e43b263a5db06d89e5dc665a1ed5",
      "okx_url": "https://web3.okx.com/token/base/0xd4e43c86334940a246daae8908c9b3cfb97c6817?ref=OKX10c",
      "o1_url": "https://o1.exchange/base/detail/0xd7548773775d7d8c65bec6b615e907a06784e43b263a5db06d89e5dc665a1ed5?ca=0xd4e43c86334940a246daae8908c9b3cfb97c6817@basescan",
      "price_change_24h": 15127.0,
      "volume_24h_usd": 1133146.25,
      "mcap_source": "dexscreener",
      "logo_url": "https://cdn.dexscreener.com/cms/images/IBNj8czzwt60NzY6?width=800&height=800&quality=95&format=auto"
    },
    {
      "rank": 2,
      "symbol": "SPIRIT",
      "token_address": "0xfd4d850dde44a4144a74d036d24933bbe550edc7",
      "score": 39.8,
      "severity": "none",
      "mcap_usd": 202122.0,
      "lp_total_usd": 57509.16,
      "lp_total_usd_24h_ago": 0.0,
      "lp_total_change_24h_pct": 0.0,
      "holder_count": 0,
      "holder_count_24h_ago": 0,
      "holder_count_change_24h_pct": 0.0,
      "top10_pct": 100.0,
      "x_username": "",
      "x_url": "",
      "signal_age_hours": 1.25,
      "pair_address": "0x8563fdf6314e8e5a12af2b9f06e764b5c5c80a19c9ecb6be78b5dc383087daa0",
      "dexscreener_url": "https://dexscreener.com/base/0x8563fdf6314e8e5a12af2b9f06e764b5c5c80a19c9ecb6be78b5dc383087daa0",
      "okx_url": "https://web3.okx.com/token/base/0xfd4d850dde44a4144a74d036d24933bbe550edc7?ref=OKX10c",
      "o1_url": "https://o1.exchange/base/detail/0x8563fdf6314e8e5a12af2b9f06e764b5c5c80a19c9ecb6be78b5dc383087daa0?ca=0xfd4d850dde44a4144a74d036d24933bbe550edc7@basescan",
      "price_change_24h": 4079.0,
      "volume_24h_usd": 1767347.22,
      "mcap_source": "dexscreener",
      "logo_url": "https://cdn.dexscreener.com/cms/images/2czxoLcsugWM_bnH?width=800&height=800&quality=95&format=auto"
    },
    {
      "rank": 3,
      "symbol": "UASTER",
      "token_address": "0xa62755a7460590f78fa7038027cf17f73f4dc1cd",
      "score": 39.1,
      "severity": "none",
      "mcap_usd": 43930.0,
      "lp_total_usd": 20904.8,
      "lp_total_usd_24h_ago": 47081.46,
      "lp_total_change_24h_pct": -50.05,
      "holder_count": 0,
      "holder_count_24h_ago": 0,
      "holder_count_change_24h_pct": 0.0,
      "top10_pct": 100.0,
      "x_username": "",
      "x_url": "",
      "signal_age_hours": 0.19,
      "pair_address": "0x7309006edc54814df25ed7358d5fed636238d7272d55af64cfa3bf54b71e2ceb",
      "dexscreener_url": "https://dexscreener.com/base/0x7309006edc54814df25ed7358d5fed636238d7272d55af64cfa3bf54b71e2ceb",
      "okx_url": "https://web3.okx.com/token/base/0xa62755a7460590f78fa7038027cf17f73f4dc1cd?ref=OKX10c",
      "o1_url": "https://o1.exchange/base/detail/0x7309006edc54814df25ed7358d5fed636238d7272d55af64cfa3bf54b71e2ceb?ca=0xa62755a7460590f78fa7038027cf17f73f4dc1cd@basescan",
      "price_change_24h": -68.69,
      "volume_24h_usd": 202925.08,
      "mcap_source": "dexscreener",
      "logo_url": "https://cdn.dexscreener.com/cms/images/Sy8PWq-LceVSxb8g?width=800&height=800&quality=95&format=auto"
    },
    {
      "rank": 4,
      "symbol": "MUSK",
      "token_address": "0xd2cdcb399438d3d088a6bb3a4f5af39a3ab01110",
      "score": 36.3,
      "severity": "none",
      "mcap_usd": 56602.0,
      "lp_total_usd": 25747.66,
      "lp_total_usd_24h_ago": 18845.01,
      "lp_total_change_24h_pct": 47.62,
      "holder_count": 0,
      "holder_count_24h_ago": 0,
      "holder_count_change_24h_pct": 0.0,
      "top10_pct": 100.0,
      "x_username": "",
      "x_url": "",
      "signal_age_hours": 0.53,
      "pair_address": "0x02ff2bd52be646552fd45920951d0a28dbbc6c0a",
      "dexscreener_url": "https://dexscreener.com/base/0x02ff2bd52be646552fd45920951d0a28dbbc6c0a",
      "okx_url": "https://web3.okx.com/token/base/0xd2cdcb399438d3d088a6bb3a4f5af39a3ab01110?ref=OKX10c",
      "o1_url": "https://o1.exchange/base/detail/0x02ff2bd52be646552fd45920951d0a28dbbc6c0a?ca=0xd2cdcb399438d3d088a6bb3a4f5af39a3ab01110@basescan",
      "price_change_24h": 66.75,
      "volume_24h_usd": 176047.4,
      "mcap_source": "dexscreener",
      "logo_url": "https://cdn.dexscreener.com/cms/images/Alf0CV5xjf7vJVrb?width=800&height=800&quality=95&format=auto"
    }
  ]
}